randomheaders/UserAgent.csv
randomheaders/__init__.py
randomheaders-1.2.dist-info/METADATA
randomheaders-1.2.dist-info/WHEEL
randomheaders-1.2.dist-info/top_level.txt
randomheaders-1.2.dist-info/RECORD
