Metadata-Version: 1.0
Name: randomheaders
Version: 1.2
Summary: Generating Random Headers/User Agents with a locally saved file
Home-page: https://github.com/theriley106/randomheaders
Author: theriley106
Author-email: christopherlambert106@gmail.com
License: MIT
Platform: UNKNOWN
